epoch_engine/__init__.py
epoch_engine/core/__init__.py
epoch_engine/core/checkpoint_handler.py
epoch_engine/core/configs.py
epoch_engine/core/plotting.py
epoch_engine/core/trainer.py
epoch_engine/core/types.py
epoch_engine/core/metrics/__init__.py
epoch_engine/core/metrics/metrics_logger.py
epoch_engine/core/metrics/metrics_tracker.py
epoch_engine/models/__init__.py
epoch_engine/models/architectures.py
epoch_engine-0.1.4.dist-info/licenses/LICENSE.txt
epoch_engine-0.1.4.dist-info/METADATA
epoch_engine-0.1.4.dist-info/WHEEL
epoch_engine-0.1.4.dist-info/top_level.txt
epoch_engine-0.1.4.dist-info/RECORD
