Metadata-Version: 2.4
Name: epoch-engine
Version: 0.1.4
Summary: A lightweight trainer and evaluator for PyTorch models with a focus on simplicity and flexibility.
Author-email: Sergey Polivin <s.polivin@gmail.com>
License: MIT
Project-URL: Homepage, https://github.com/spolivin/epoch-engine
Project-URL: Issues, https://github.com/spolivin/epoch-engine/issues
Project-URL: Pull-requests, https://github.com/spolivin/epoch-engine/pulls
Project-URL: Source, https://github.com/spolivin/epoch-engine/tree/master/epoch_engine
Keywords: pytorch,deep-learning
Classifier: Programming Language :: Python :: 3
Classifier: License :: OSI Approved :: MIT License
Classifier: Operating System :: OS Independent
Classifier: Development Status :: 3 - Alpha
Requires-Python: >=3.8
License-File: LICENSE.txt
Requires-Dist: torch==2.5.0
Requires-Dist: torchvision==0.20.0
Requires-Dist: tqdm==4.67.0
Requires-Dist: matplotlib==3.10.5
Requires-Dist: numpy==2.2.6
Provides-Extra: build
Requires-Dist: setuptools; extra == "build"
Requires-Dist: wheel; extra == "build"
Requires-Dist: build; extra == "build"
Requires-Dist: twine; extra == "build"
Provides-Extra: linters
Requires-Dist: black; extra == "linters"
Requires-Dist: isort; extra == "linters"
Requires-Dist: pre-commit; extra == "linters"
Dynamic: license-file
